opencensus_ext_newrelic/__init__.py
opencensus_ext_newrelic/stats.py
opencensus_ext_newrelic/trace.py
opencensus_ext_newrelic/version.py
opencensus_ext_newrelic-0.2.1.dist-info/LICENSE
opencensus_ext_newrelic-0.2.1.dist-info/METADATA
opencensus_ext_newrelic-0.2.1.dist-info/THIRD_PARTY_NOTICES.rst
opencensus_ext_newrelic-0.2.1.dist-info/WHEEL
opencensus_ext_newrelic-0.2.1.dist-info/top_level.txt
opencensus_ext_newrelic-0.2.1.dist-info/RECORD
