Metadata-Version: 2.1
Name: opencensus-ext-newrelic
Version: 0.2.1
Summary: New Relic OpenCensus Exporter
Home-page: https://github.com/newrelic/newrelic-opencensus-exporter-python
Author: New Relic
Author-email: open-source@newrelic.com
License: Apache-2.0
Platform: any
Classifier: Development Status :: 3 - Alpha
Classifier: Topic :: System :: Monitoring
Classifier: Programming Language :: Python :: Implementation :: PyPy
Classifier: Programming Language :: Python :: Implementation :: CPython
Classifier: Programming Language :: Python :: 2
Classifier: Programming Language :: Python :: 2.7
Classifier: Programming Language :: Python :: 3
Classifier: Programming Language :: Python :: 3.5
Classifier: Programming Language :: Python :: 3.6
Classifier: Programming Language :: Python :: 3.7
Classifier: Operating System :: OS Independent
Classifier: License :: OSI Approved :: Apache Software License
Requires-Python: !=3.0.*,!=3.1.*,!=3.2.*,!=3.3.*,!=3.4.*,>=2.7
Requires-Dist: opencensus (~=0.7)
Requires-Dist: newrelic-telemetry-sdk (<0.5,>=0.4.0)
